special4pm/__init__.py
special4pm/bootstrap/__init__.py
special4pm/bootstrap/bootstrap.py
special4pm/estimation/__init__.py
special4pm/estimation/metrics.py
special4pm/estimation/species_estimator.py
special4pm/raripolation/__init__.py
special4pm/raripolation/extrapolation.py
special4pm/raripolation/rarefaction.py
special4pm/raripolation/rarefaction_extrapolation.py
special4pm/simulation/__init__.py
special4pm/simulation/simulation.py
special4pm/species/__init__.py
special4pm/species/species_retrieval.py
special4pm/visualization/__init__.py
special4pm/visualization/plot_diversity_profiles.py
special4pm/visualization/plots.py
special4pm/visualization/visualization.py
special4pm-0.1.3.dist-info/METADATA
special4pm-0.1.3.dist-info/WHEEL
special4pm-0.1.3.dist-info/licenses/LICENSE
special4pm-0.1.3.dist-info/RECORD
