Metadata-Version: 2.3
Name: special4pm
Version: 0.1.3
Summary: A Python package for the species-based analysis and computation of event logs
Project-URL: Homepage, https://github.com/MartinKabierski/SpeciAL-core
Author-email: Martin Kabierski <martin.kabierski@hu-berlin.de>
License-File: LICENSE
Classifier: License :: OSI Approved :: MIT License
Classifier: Operating System :: OS Independent
Classifier: Programming Language :: Python :: 3
Requires-Python: >=3.8
Requires-Dist: matplotlib>=3.6
Requires-Dist: numpy>=1.26
Requires-Dist: pandas>=1.5
Requires-Dist: pm4py>=2.5
Requires-Dist: scipy>=1.10
Requires-Dist: tqdm>=4.64
